{
  "unversionedId": "infra/README",
  "id": "infra/README",
  "title": "Infrastructure",
  "description": "Please use the links below to reference architectures for common osmosis infrastructure setups.",
  "source": "@site/docs/infra/README.md",
  "sourceDirName": "infra",
  "slug": "/infra/",
  "permalink": "/docs/infra/",
  "draft": false,
  "editUrl": "https://github.com/facebook/docusaurus/tree/main/packages/create-docusaurus/templates/shared/docs/infra/README.md",
  "tags": [],
  "version": "current",
  "frontMatter": {},
  "sidebar": "tutorialSidebar",
  "previous": {
    "title": "History of Changes",
    "permalink": "/docs/history-and-changes"
  },
  "next": {
    "title": "Load balanced RPC setup with Alerts",
    "permalink": "/docs/infra/do/loadbalanced-rpc-with-monitor-alerts"
  }
}